LICENSE
MANIFEST.in
README.md
setup.py
grpc_tls/__init__.py
grpc_tls/constants.py
grpc_tls/settings.py
grpc_tls.egg-info/PKG-INFO
grpc_tls.egg-info/SOURCES.txt
grpc_tls.egg-info/dependency_links.txt
grpc_tls.egg-info/requires.txt
grpc_tls.egg-info/top_level.txt
grpc_tls/management/__init__.py
grpc_tls/management/commands/__init__.py
grpc_tls/management/commands/grpc_tls.py